entxpy/__init__.py
entxpy/errors.py
entx_py-1.0.2.dist-info/METADATA
entx_py-1.0.2.dist-info/WHEEL
entx_py-1.0.2.dist-info/licenses/LICENSE
entx_py-1.0.2.dist-info/RECORD
