Metadata-Version: 2.1
Name: entx-py
Version: 1.0.2
Summary: The python file encryption library.
Project-URL: Homepage, https://github.com/MaskdDev/entxpy
Project-URL: Bug Tracker, https://github.com/MaskdDev/entxpy/issues
Author-email: MaskdDev <maskddev@gmail.com>
License-File: LICENSE
Classifier: License :: OSI Approved :: MIT License
Classifier: Operating System :: OS Independent
Classifier: Programming Language :: Python :: 3
Requires-Python: >=3.10
Requires-Dist: entx==3.1.0
